EX/pu-2-dm/pu.vh
`timescale 1ns/10ps
`define ASSERT 1'b1
`define NEGATE 1'b0

`define WIDTH 15 // data width 15:0
`define HALFWIDTH 7 // half data width 7:0

`define RAS 3 // 3:0 r0, r1, r2, r3 register addresses size
`define RASB 1 // 1:0 register address size bit for addressing

`define OPS 2 // 2:0 operator size

`define PCS 5 // 5:0 program counter size

//`define CMDS 9 // 9:0 command size  HALT + RASB+1 + OPS+1 + RASB+1 + RASB+1
`define CMDS `WIDTH // see dec.v
`define LICMDS 1 // 1:0 00,01 do nothing 10 load low 11 load high

`define LIDXS 1 // 1:0 00,01 do nothing / 10 LIL / 11 LIH

`define LIDXENUM typedef enum {THU, IMM, LIL, LIH} LIDEXNUM;

`define DMS 255  // 255:0 data memory size
`define DMSB 7 // 7:0 data memory addr size

EX/pu-3-cond/sel.v
`include "pu.vh"
module sel(input [`WIDTH:0] a, b, input s, output logic [`WIDTH:0] o);
	always_comb
		if(s) o = b;
		else o = a;
endmodule

EX/pu-2-dm/dmem.v
`include "pu.vh"
module dmem(input [`DMSB:0] ad, input [`WIDTH:0] wd, input we, output [`WIDTH:0] rd, input clk);
	logic [`WIDTH:0] dm [`DMS:0];
	assign rd = dm[ad];
	always @(posedge clk) begin
		if(we) dm[ad] <= wd;
	end
endmodule

EX/pu-2-dm/dec.v
`include "pu.vh"

module dec(input [`CMDS:0] o, output logic h, we, output logic [`RASB:0] wad,
	output logic [`OPS:0] op, output logic [`RASB:0] brad, arad,
	output logic [`LICMDS:0] liop, output logic [`HALFWIDTH:0] iv,
	output logic dmwe, dms);
/*
F E D C B A 9 8 7 6 5 4 3 2 1 0
0 0 0 0 * * * * * * * * * 0 * 0 ; NOP
0 0 0 0 * * * * * * * * * 0 * 1 ; HALT
0 0 0 0 rw> a-> * op -> * 1 b-> ; CAL rw=ra,rb
0 0 0 1 rw> a-> * op -> * 1 b-> ; LM rw=[ra op rb]
0 0 1 o rw> a-> im------------> ; CAL rw=ra,im
0 1 0 0 rw> a-> im------------> ; LIL rw=ra,im
0 1 0 1 rw> a-> im------------> ; LIH rw=ra,im
1 0 0 o rw> a-> im------------> ; LM rw=[ra o im] o=0:ADD/1:SUB
1 0 1 o b-> a-> im------------> ; SM [ra o im]=rb
*/
//	`LIDXENUM
	always @* begin
		h = `NEGATE;
		arad = 0;
		brad = 0;
		op = 0;
		we = `NEGATE;
		wad = 0;
		liop = THU;
		iv = 0;
		dmwe = `NEGATE;
		dms = `NEGATE;
		case(o[15:13])
		// synopsys full_case parallel_case
		3'b000: begin
			case(o[2])
			// synopsys full_case parallel_case
			`NEGATE: begin
				if(o[0] == `NEGATE) begin
// F E D C B A 9 8 7 6 5 4 3 2 1 0
// 0 0 0 * * * * * * * * * * 0 * 0 ; NOP
				end else begin
// F E D C B A 9 8 7 6 5 4 3 2 1 0
// 0 0 0 * * * * * * * * * * 0 * 1 ; HALT
					h = `ASSERT;
				end

			end
			`ASSERT: begin
				case(o[12])
				// synopsys full_case parallel_case
				`NEGATE: begin
// F E D C B A 9 8 7 6 5 4 3 2 1 0
// 0 0 0 0 rw> a-> * op -> * 1 b-> ; CAL rw=ra,rb
					wad = o[11:10];
					we = `ASSERT;
					arad = o[9:8];
					op = o[6:4];
					brad = o[1:0];
				end
				`ASSERT: begin
// F E D C B A 9 8 7 6 5 4 3 2 1 0
// 0 0 0 1 rw> a-> * op -> * 1 b-> ; LM rw=[ra op rb]
					wad = o[11:10];
					we = `ASSERT;
					arad = o[9:8];
					op = o[6:4];
					brad = o[1:0];
					dms = `ASSERT;
				end
				endcase
			end
			endcase
		end
		3'b001: begin
// F E D C B A 9 8 7 6 5 4 3 2 1 0
// 0 0 1 o rw> a-> im------------> ; CAL rw=ra,im
			wad = o[11:10];
			we = `ASSERT;
			op = {2'b00,o[12]};
			arad = o[9:8];
			liop = IMM;
		end
		3'b010: begin
			case(o[12])
			// synopsys full_case parallel_case
			`NEGATE: begin
// F E D C B A 9 8 7 6 5 4 3 2 1 0
// 0 1 0 0 rw> a-> im------------> ; LIL rw=ra,im
				wad = o[11:10];
				we = `ASSERT;
				brad = o[9:8];
				op = 3'b010; // TRU
				liop = LIL;
				iv = o[`HALFWIDTH:0];
			end
			`ASSERT: begin
// F E D C B A 9 8 7 6 5 4 3 2 1 0
// 0 1 0 1 rw> a-> im------------> ; LIH rw=ra,im
				wad = o[11:10];
				we = `ASSERT;
				brad = o[9:8];
				op = 3'b010; // TRU
				liop = LIH;
				iv = o[`HALFWIDTH:0];
			end
			endcase	
		end
		3'b100: begin
// F E D C B A 9 8 7 6 5 4 3 2 1 0
// 1 0 0 o rw> a-> im------------> ; LM rw=[ra o im]
			wad = o[11:10];
			we = `ASSERT;
			arad = o[9:8];
			op = {2'b00,o[12]}; // ADD/SUB
			liop = IMM;
			iv = o[`HALFWIDTH:0];
		end
		3'b101: begin
// F E D C B A 9 8 7 6 5 4 3 2 1 0
// 1 0 1 o b-> a-> im------------> ; SM [ra o im]=rb
			brad = o[11:10];
			we = `ASSERT;
			arad = o[9:8];
			op = {2'b00,o[12]}; // ADD/SUB
			liop = IMM;
			iv = o[`HALFWIDTH:0];
			dmwe = `ASSERT;
		end
		endcase
	end
endmodule

EX/pu-2-dm/imem.v
`include "pu.vh"
module imem(input [`PCS:0] pc, output logic [`CMDS:0] o);
	always_comb
		case(pc)
		// synopsys full_case parallel_case
		5'h00: o = 16'b0100_0000_1010_1001; // LIL r0, r0, 8'b10101001
		5'h01: o = 16'b0101_0000_0000_0100; // LIH r0, r0, 8'b00000100
		5'h02: o = 16'b0100_0101_0101_0110; // LIL r1, r1, 8'b01010110
		5'h03: o = 16'b0101_0101_0000_0100; // LIH r1, r1, 8'b00000100
		5'h04: o = 16'b0000_1000_0000_0101; // add r2=r0,r1
		5'h05: o = 16'b0100_1111_0000_0001; // LIL r3, r3, 8'b00000001
		5'h06: o = 16'b0101_1111_0000_0000; // LIH r3, r3, 8'b00000000
		5'h07: o = 16'b1010_0011_0000_0001; // SM [r3 + 00000001]=r0
		5'h08: o = 16'b0100_1111_0000_0000; // LIL r3, r3, 8'b00000000
		5'h09: o = 16'b0101_1111_0000_0000; // LIH r3, r3, 8'b00000000
		5'h0a: o = 16'b1000_0111_0000_0010; // LM r1=[r3 + 00000010]
		5'h0b: o = 16'b0000_0000_0000_0001; // HALT
		endcase
endmodule

/*
F E D C B A 9 8 7 6 5 4 3 2 1 0
0 0 0 0 * * * * * * * * * 0 * 0 ; NOP
0 0 0 0 * * * * * * * * * 0 * 1 ; HALT
0 0 0 0 rw> a-> * op -> * 1 b-> ; CAL rw=ra,rb
0 0 0 1 rw> a-> * op -> * 1 b-> ; LM rw=[ra op rb]
0 0 1 o rw> a-> im------------> ; CAL rw=ra,im
0 1 0 0 rw> a-> im------------> ; LIL rw=ra,im
0 1 0 1 rw> a-> im------------> ; LIH rw=ra,im
1 0 0 o rw> a-> im------------> ; LM rw=[ra o im] o=0:ADD/1:SUB
1 0 1 o b-> a-> im------------> ; SM [ra o im]=rb
*/

EX/pu-2-dm/pc.v
`include "pu.vh"
module pc(input halt, output logic [`PCS:0] pc, input clk, rst);
	always @(posedge clk or posedge rst)
		if(rst) pc <= 0;
		else if(!halt) pc <= pc + 1;
endmodule

EX/pu-2-dm/alu.v
`include "pu.vh"
module alu(input [`WIDTH:0] a, b, input [`OPS:0] op, output logic [`WIDTH:0] r);
//	enum {ADD, SUB, THU, ASL, RSL, RSR, NAD, XOR} OPETYP;
	parameter ADD=0, SUB=1, THU=2, ASL=3, RSL=4, RSR=5, NAD=6, XOR=7;
	always @*
		case(op)
		// synopsys full_case parallel_case
		ADD: r = a+b;	
		SUB: r = a-b;
		THU: r = b;
		ASL: r = a>>>b;
		RSL: r = a>>b;
		RSR: r = a<<b;
		NAD: r = ~(a&b);
		XOR: r = a^b;
		endcase
endmodule

EX/pu-2-dm/lidx.v
`include "pu.vh"
module lidx(input [`WIDTH:0] i, input [`HALFWIDTH:0] iv, input [`LIDXS:0] op, output logic [`WIDTH:0] o);
//	`LIDXENUM
	always @*
		casex(op)
		// synopsys full_case parallel_case
		THU:
			o = i;
		IMM:
			o = {8'h00,iv};
		LIL:
			o = {i[`WIDTH:`HALFWIDTH+1],iv};
		LIH:
			o = {iv,i[`HALFWIDTH:0]};
		endcase
endmodule

EX/pu-3-cond/rega.v
`include "pu.vh"
module rega(input logic [`RASB:0] arad, brad, output logic [`WIDTH:0] a, b,
	input we, input logic [`RASB:0] wad, input [`WIDTH:0] wd,
	input clk, rst);
	logic [`WIDTH:0] regar [`RAS:0];
	always @(posedge clk or posedge rst) begin
		if(rst) begin
			regar[0] <= 0;
			regar[1] <= 0;
			regar[2] <= 0;
			regar[3] <= 0;
		end else if(we) regar[wad] <= wd;
	end
	assign a = regar[arad];
	assign b = regar[brad];
endmodule

EX/pu-2-dm/pu.v
`include "pu.vh"
module pu(output we, output logic [`WIDTH:0] wd, input clk, rst);
	logic [`WIDTH:0] a, b, bo, lp, dmrd;
	logic [`HALFWIDTH:0] iv;
	logic [`RASB:0] arad, brad, wad;
	logic [`OPS:0] op;
	logic [`PCS:0] pca;
	logic [`CMDS:0] o;
	logic [`LICMDS:0] liop;
	rega rega(arad, brad, a, b, we, wad, wd, clk, rst);
	lidx lidx(b, iv, liop, bo);
	alu alu(a, bo, op, lp);
	pc pc(h, pca, clk, rst);
	imem imem(pca, o);
	dec dec(o, h, we, wad, op, brad, arad, liop, iv, dmwe, dms);
	dmem dmem(lp[`DMSB:0], bo, dmwe, dmrd, clk);
	sel dmsel (lp, dmrd, dms, wd);
endmodule

EX/pu-1-imm/test.v
`include "pu.vh"
module test;
	logic clk, rst;
	wire re;
	wire [`WIDTH:0] wd;
	pu pu(we, wd, clk, rst);
	always #5 clk =~ clk;
initial begin
$dumpfile("pu.vcd");
$dumpvars(0, pu);
rst = 1;
clk = 0;
#20
rst = 0;
#500
$finish;
end
endmodule

EX/pu-2-dm/pu.vcd
$date
	Fri Jun 18 09:05:57 2021
$end
$version
	Icarus Verilog
$end
$timescale
	10ps
$end
$scope module test $end
$scope module pu $end
$var wire 1 ! clk $end
$var wire 1 " rst $end
$var wire 1 # we $end
$var wire 16 $ wd [15:0] $end
$var wire 2 % wad [1:0] $end
$var wire 6 & pca [5:0] $end
$var wire 3 ' op [2:0] $end
$var wire 16 ( o [15:0] $end
$var wire 16 ) lp [15:0] $end
$var wire 2 * liop [1:0] $end
$var wire 8 + iv [7:0] $end
$var wire 1 , h $end
$var wire 1 - dmwe $end
$var wire 1 . dms $end
$var wire 16 / dmrd [15:0] $end
$var wire 2 0 brad [1:0] $end
$var wire 16 1 bo [15:0] $end
$var wire 16 2 b [15:0] $end
$var wire 2 3 arad [1:0] $end
$var wire 16 4 a [15:0] $end
$scope module alu $end
$var wire 3 5 op [2:0] $end
$var wire 16 6 b [15:0] $end
$var wire 16 7 a [15:0] $end
$var reg 16 8 r [15:0] $end
$upscope $end
$scope module dec $end
$var wire 16 9 o [15:0] $end
$var reg 2 : arad [1:0] $end
$var reg 2 ; brad [1:0] $end
$var reg 1 . dms $end
$var reg 1 - dmwe $end
$var reg 1 , h $end
$var reg 8 < iv [7:0] $end
$var reg 2 = liop [1:0] $end
$var reg 3 > op [2:0] $end
$var reg 2 ? wad [1:0] $end
$var reg 1 # we $end
$upscope $end
$scope module dmem $end
$var wire 8 @ ad [7:0] $end
$var wire 1 ! clk $end
$var wire 16 A rd [15:0] $end
$var wire 1 - we $end
$var wire 16 B wd [15:0] $end
$upscope $end
$scope module dmsel $end
$var wire 16 C a [15:0] $end
$var wire 16 D b [15:0] $end
$var wire 1 . s $end
$var reg 16 E o [15:0] $end
$upscope $end
$scope module imem $end
$var wire 6 F pc [5:0] $end
$var reg 16 G o [15:0] $end
$upscope $end
$scope module lidx $end
$var wire 8 H iv [7:0] $end
$var wire 2 I op [1:0] $end
$var wire 16 J i [15:0] $end
$var reg 16 K o [15:0] $end
$upscope $end
$scope module pc $end
$var wire 1 ! clk $end
$var wire 1 , halt $end
$var wire 1 " rst $end
$var reg 6 L pc [5:0] $end
$upscope $end
$scope module rega $end
$var wire 16 M a [15:0] $end
$var wire 2 N arad [1:0] $end
$var wire 16 O b [15:0] $end
$var wire 2 P brad [1:0] $end
$var wire 1 ! clk $end
$var wire 1 " rst $end
$var wire 2 Q wad [1:0] $end
$var wire 16 R wd [15:0] $end
$var wire 1 # we $end
$upscope $end
$upscope $end
$upscope $end
$enddefinitions $end
#0
$dumpvars
b10101001 R
b0 Q
b0 P
b0 O
b0 N
b0 M
b0 L
b10101001 K
b0 J
b10 I
b10101001 H
b100000010101001 G
b0 F
b10101001 E
bx D
b10101001 C
b10101001 B
bx A
b10101001 @
b0 ?
b10 >
b10 =
b10101001 <
b0 ;
b0 :
b100000010101001 9
b10101001 8
b0 7
b10101001 6
b10 5
b0 4
b0 3
b0 2
b10101001 1
b0 0
bx /
0.
0-
0,
b10101001 +
b10 *
b10101001 )
b100000010101001 (
b10 '
b0 &
b0 %
b10101001 $
1#
1"
0!
$end
#500
1!
#1000
0!
#1500
1!
#2000
0!
0"
#2500
b10010101001 $
b10010101001 E
b10010101001 R
b10010101001 )
b10010101001 8
b10010101001 C
b10010101001 1
b10010101001 6
b10010101001 B
b10010101001 K
b100 +
b100 <
b100 H
b11 *
b11 =
b11 I
1#
b10 '
b10 5
b10 >
b101000000000100 (
b101000000000100 9
b101000000000100 G
b1 &
b1 F
b1 L
b10101001 4
b10101001 7
b10101001 M
b10101001 2
b10101001 J
b10101001 O
1!
#3000
0!
#3500
b1010110 $
b1010110 E
b1010110 R
b1010110 @
b1010110 )
b1010110 8
b1010110 C
b1010110 1
b1010110 6
b1010110 B
b1010110 K
b1 0
b1 ;
b1 P
b1 %
b1 ?
b1 Q
b1010110 +
b1010110 <
b1010110 H
b10 *
b10 =
b10 I
1#
b10 '
b10 5
b10 >
b100010101010110 (
b100010101010110 9
b100010101010110 G
b10010101001 4
b10010101001 7
b10010101001 M
b0 2
b0 J
b0 O
b10 &
b10 F
b10 L
1!
#4000
0!
#4500
b10001010110 $
b10001010110 E
b10001010110 R
b10001010110 )
b10001010110 8
b10001010110 C
b10001010110 1
b10001010110 6
b10001010110 B
b10001010110 K
b100 +
b100 <
b100 H
b11 *
b11 =
b11 I
b1 %
b1 ?
b1 Q
1#
b10 '
b10 5
b10 >
b1 0
b1 ;
b1 P
b101010100000100 (
b101010100000100 9
b101010100000100 G
b11 &
b11 F
b11 L
b1010110 2
b1010110 J
b1010110 O
1!
#5000
0!
#5500
b100011111111 $
b100011111111 E
b100011111111 R
b11111111 @
b100011111111 )
b100011111111 8
b100011111111 C
b0 +
b0 <
b0 H
b0 *
b0 =
b0 I
b10 %
b10 ?
b10 Q
1#
b0 '
b0 5
b0 >
b1 0
b1 ;
b1 P
b100000000101 (
b100000000101 9
b100000000101 G
b10001010110 2
b10001010110 J
b10001010110 O
b100 &
b100 F
b100 L
1!
#6000
0!
#6500
b1 $
b1 E
b1 R
b1 @
b1 )
b1 8
b1 C
b1 1
b1 6
b1 B
b1 K
b1 +
b1 <
b1 H
b10 *
b10 =
b10 I
b10 '
b10 5
b10 >
b11 %
b11 ?
b11 Q
1#
b0 2
b0 J
b0 O
b11 0
b11 ;
b11 P
b100111100000001 (
b100111100000001 9
b100111100000001 G
b101 &
b101 F
b101 L
1!
#7000
0!
#7500
b0 +
b0 <
b0 H
b11 *
b11 =
b11 I
b11 %
b11 ?
b11 Q
1#
b10 '
b10 5
b10 >
b11 0
b11 ;
b11 P
b101111100000000 (
b101111100000000 9
b101111100000000 G
b1 2
b1 J
b1 O
b110 &
b110 F
b110 L
1!
#8000
0!
#8500
b10 $
b10 E
b10 R
b10 @
b10 )
b10 8
b10 C
1-
b1 +
b1 <
b1 H
b1 4
b1 7
b1 M
b11 3
b11 :
b11 N
b1 *
b1 =
b1 I
b0 %
b0 ?
b0 Q
1#
b0 '
b0 5
b0 >
b10010101001 2
b10010101001 J
b10010101001 O
b0 0
b0 ;
b0 P
b1010001100000001 (
b1010001100000001 9
b1010001100000001 G
b111 &
b111 F
b111 L
1!
#9000
0!
#9500
b0 $
b0 E
b0 R
b0 @
b0 1
b0 6
b0 B
b0 K
b0 )
b0 8
b0 C
b10 '
b10 5
b10 >
b11 0
b11 ;
b11 P
b11 %
b11 ?
b11 Q
0-
b0 +
b0 <
b0 H
b10 *
b10 =
b10 I
1#
b10 4
b10 7
b10 M
b0 3
b0 :
b0 N
b100111100000000 (
b100111100000000 9
b100111100000000 G
bx /
bx A
bx D
b1 2
b1 J
b1 O
b1000 &
b1000 F
b1000 L
1!
#10000
0!
#10500
b11 *
b11 =
b11 I
b11 %
b11 ?
b11 Q
1#
b10 '
b10 5
b10 >
b11 0
b11 ;
b11 P
b101111100000000 (
b101111100000000 9
b101111100000000 G
b1001 &
b1001 F
b1001 L
b0 2
b0 J
b0 O
1!
#11000
0!
#11500
b10 $
b10 E
b10 R
b1 /
b1 A
b1 D
b10 @
b10 )
b10 8
b10 C
b10 1
b10 6
b10 B
b10 K
b10 +
b10 <
b10 H
b0 4
b0 7
b0 M
b11 3
b11 :
b11 N
b1 *
b1 =
b1 I
b1 %
b1 ?
b1 Q
1#
b0 '
b0 5
b0 >
b10 2
b10 J
b10 O
b0 0
b0 ;
b0 P
b1000011100000010 (
b1000011100000010 9
b1000011100000010 G
b1010 &
b1010 F
b1010 L
1!
#12000
0!
#12500
b100 $
b100 E
b100 R
bx /
bx A
bx D
b100 @
b100 )
b100 8
b100 C
1,
b0 +
b0 <
b0 H
b0 *
b0 =
b0 I
b0 %
b0 ?
b0 Q
0#
b10 4
b10 7
b10 M
b0 3
b0 :
b0 N
b1 (
b1 9
b1 G
b1011 &
b1011 F
b1011 L
1!
